HISTORY.rst
LICENSE
MANIFEST.in
README.rst
setup.py
Flask_Heroku_Auth.egg-info/PKG-INFO
Flask_Heroku_Auth.egg-info/SOURCES.txt
Flask_Heroku_Auth.egg-info/dependency_links.txt
Flask_Heroku_Auth.egg-info/not-zip-safe
Flask_Heroku_Auth.egg-info/requires.txt
Flask_Heroku_Auth.egg-info/top_level.txt
flask_heroku_auth/__init__.py
flask_heroku_auth/api.py
flask_heroku_auth/core.py
flask_heroku_auth/oauth.py
flask_heroku_auth/utils.py