Metadata-Version: 1.1
Name: Flask-Heroku-Auth
Version: 0.0.5
Summary: Flask Based Heroku Authentication.
Home-page: http://github.com/rhyselsmore/flask-heroku-auth
Author: Rhys Elsmore
Author-email: me@rhys.io
License: Copyright 2013 Rhys Elsmore
